{"timestamp":"2016-10-13T15:55:00+0200","id":124041,"name":"Sophie","coordinate":{"longitude":11.5777998,"latitude":48.14989853},"fuelLevel":0.86,"lastAddress":"Schellingstraße 16, 80799 München, Germany"}
{"timestamp":"2016-10-13T15:55:00+0200","id":124026,"name":"Eva","coordinate":{"longitude":11.57900047,"latitude":48.15390015},"fuelLevel":0.61,"lastAddress":"Türkenstraße 104, 80799 München, Germany"}
{"timestamp":"2016-10-13T15:55:00+0200","id":124025,"name":"Elli","coordinate":{"longitude":11.57670021,"latitude":48.15769958},"fuelLevel":0.87,"lastAddress":"Franz-Joseph-Straße 41, 80801 München, Germany"}
{"timestamp":"2016-10-13T15:55:00+0200","id":124033,"name":"Johanna","coordinate":{"longitude":11.57699966,"latitude":48.15029907},"fuelLevel":0.73,"lastAddress":"Schellingstraße 24, 80799 München, Germany"}
{"timestamp":"2016-10-13T15:55:00+0200","id":124036,"name":"Liesel","coordinate":{"longitude":11.57870007,"latitude":48.14960098},"fuelLevel":0.9400000000000001,"lastAddress":"Schellingstraße 10, 80799 München, Germany"}
{"timestamp":"2016-10-13T15:55:00+0200","id":124044,"name":"Uschi","coordinate":{"longitude":11.57269955,"latitude":48.13190079},"fuelLevel":0.9199999999999999,"lastAddress":"Müllerstraße 7, 80469 München, Germany"}
{"timestamp":"2016-10-13T15:55:00+0200","id":124040,"name":"Reserl","coordinate":{"longitude":11.57190037,"latitude":48.13140106},"fuelLevel":0.83,"lastAddress":"Müllerstraße 17, 80469 München, Germany"}
{"timestamp":"2016-10-13T15:55:00+0200","id":124021,"name":"Xaver","coordinate":{"longitude":11.58040047,"latitude":48.13010025},"fuelLevel":0.9199999999999999,"lastAddress":"Erhardtstraße 27, 80469 München, Germany"}
{"timestamp":"2016-10-13T15:55:00+0200","id":124014,"name":"Quirin","coordinate":{"longitude":11.59739971,"latitude":48.13470078},"fuelLevel":0.57,"lastAddress":"Innere Wiener Straße 59, 81667 München, Germany"}
{"timestamp":"2016-10-13T15:55:00+0200","id":124034,"name":"Kathi","coordinate":{"longitude":11.60239983,"latitude":48.12960052},"fuelLevel":0.82,"lastAddress":"Breisacher Str. 2, 81667 München, Germany"}
{"timestamp":"2016-10-13T15:55:00+0200","id":124023,"name":"Babsi","coordinate":{"longitude":11.56239986,"latitude":48.12639999},"fuelLevel":0.9,"lastAddress":"Thalkirchner Str. 76, 80337 München, Germany"}
{"timestamp":"2016-10-13T15:55:00+0200","id":124038,"name":"Magda","coordinate":{"longitude":11.60009956,"latitude":48.1283989},"fuelLevel":0.67,"lastAddress":"Pariser Pl., 81667 München, Germany"}
{"timestamp":"2016-10-13T15:55:00+0200","id":124000,"name":"Bertl","coordinate":{"longitude":11.59790039,"latitude":48.12630081},"fuelLevel":0.8,"lastAddress":"Rosenheimer Str. 117, 81667 München, Germany"}
{"timestamp":"2016-10-13T15:55:00+0200","id":124013,"name":"Poldi","coordinate":{"longitude":11.59440041,"latitude":48.12770081},"fuelLevel":0.6000000000000001,"lastAddress":"Balanstraße 6A, 81669 München, Germany"}
{"timestamp":"2016-10-13T15:55:00+0200","id":124011,"name":"Maxl","coordinate":{"longitude":11.5951004,"latitude":48.12779999},"fuelLevel":0.6699999999999999,"lastAddress":"Rosenheimer Str. 66, 81669 München, Germany"}
{"timestamp":"2016-10-13T15:55:00+0200","id":124003,"name":"Franzl","coordinate":{"longitude":11.59309959,"latitude":48.1271019},"fuelLevel":0.8,"lastAddress":"Rablstraße 39, 81669 München, Germany"}
{"timestamp":"2016-10-13T15:55:00+0200","id":124010,"name":"Luitpold","coordinate":{"longitude":11.58419991,"latitude":48.12770081},"fuelLevel":0.9400000000000001,"lastAddress":"Zeppelinstraße 43A, 81669 München, Germany"}
{"timestamp":"2016-10-13T15:55:00+0200","id":124006,"name":"Gustl","coordinate":{"longitude":11.57479954,"latitude":48.12020111},"fuelLevel":0.9500000000000001,"lastAddress":"Oefelestraße 5, 81543 München, Germany"}
{"timestamp":"2016-10-13T15:55:00+0200","id":124020,"name":"Vinzenz","coordinate":{"longitude":11.5781002,"latitude":48.1228981},"fuelLevel":0.81,"lastAddress":"Entenbachstraße 26, 81541 München, Germany"}
{"timestamp":"2016-10-13T15:55:00+0200","id":124049,"name":"Marei","coordinate":{"longitude":11.57409954,"latitude":48.12260056},"fuelLevel":0.9400000000000001,"lastAddress":"Eduard-Schmid-Straße 34, 81541 München, Germany"}
{"timestamp":"2016-10-13T15:55:00+0200","id":124045,"name":"Vroni","coordinate":{"longitude":11.56509972,"latitude":48.12419891},"fuelLevel":0.64,"lastAddress":"Kapuzinerstraße 37, 80469 München, Germany"}
{"timestamp":"2016-10-13T15:55:00+0200","id":124018,"name":"Toni","coordinate":{"longitude":11.56980038,"latitude":48.12979889},"fuelLevel":0.66,"lastAddress":"Hans-Sachs-Straße 10, 80469 München, Germany"}
{"timestamp":"2016-10-13T15:55:00+0200","id":124012,"name":"Peter","coordinate":{"longitude":11.5614996,"latitude":48.15470123},"fuelLevel":0.9500000000000001,"lastAddress":"Schleißheimer Str. 86, 80797 München, Germany"}
{"timestamp":"2016-10-13T15:55:00+0200","id":124031,"name":"Heidi","coordinate":{"longitude":11.56659985,"latitude":48.15179825},"fuelLevel":0.6499999999999999,"lastAddress":"Heßstraße 42, 80798 München, Germany"}
{"timestamp":"2016-10-13T15:55:00+0200","id":124047,"name":"Walli","coordinate":{"longitude":11.5703001,"latitude":48.1493988},"fuelLevel":0.71,"lastAddress":"Theresienstraße, 80333 München, Germany"}
{"timestamp":"2016-10-13T15:55:00+0200","id":124002,"name":"Ferdl","coordinate":{"longitude":11.56270027,"latitude":48.15499878},"fuelLevel":0.9444444444444444,"lastAddress":"Zentnerstraße 7, 80798 München, Germany"}
{"timestamp":"2016-10-13T15:55:00+0200","id":124048,"name":"Wiggerl","coordinate":{"longitude":11.58100033,"latitude":48.16260147},"fuelLevel":0.66,"lastAddress":"Herzogstraße 29, 80803 München, Germany"}
{"timestamp":"2016-10-13T15:55:00+0200","id":124028,"name":"Gitte","coordinate":{"longitude":11.57590008,"latitude":48.16030121},"fuelLevel":0.76,"lastAddress":"Hohenzollernstraße 76-78, 80801 München, Germany"}
{"timestamp":"2016-10-13T15:55:00+0200","id":124027,"name":"Fanni","coordinate":{"longitude":11.58450031,"latitude":48.16070175},"fuelLevel":0.7899999999999999,"lastAddress":"Kaiserstraße 12, 80801 München, Germany"}
{"timestamp":"2016-10-13T15:55:00+0200","id":124005,"name":"Georg","coordinate":{"longitude":11.57549953,"latitude":48.16210175},"fuelLevel":0.56,"lastAddress":"Viktor-Scheffel-Straße 20, 80803 München, Germany"}
{"timestamp":"2016-10-13T15:55:00+0200","id":124032,"name":"Irmi","coordinate":{"longitude":11.57269955,"latitude":48.16009903},"fuelLevel":0.64,"lastAddress":"Isabellastraße 47, 80796 München, Germany"}
{"timestamp":"2016-10-13T15:55:00+0200","id":124037,"name":"Luise","coordinate":{"longitude":11.57019997,"latitude":48.15769958},"fuelLevel":0.52,"lastAddress":"Agnesstraße 14, 80798 München, Germany"}
{"timestamp":"2016-10-13T15:55:00+0200","id":124017,"name":"Siggi","coordinate":{"longitude":11.57260036,"latitude":48.15999985},"fuelLevel":0.56,"lastAddress":"Isabellastraße 45, 80796 München, Germany"}
{"timestamp":"2016-10-13T15:55:00+0200","id":124029,"name":"Hannah","coordinate":{"longitude":11.51049995,"latitude":48.04539871},"fuelLevel":0.7,"lastAddress":"Gistlstraße 159, 82049 Pullach im Isartal, Germany"}
{"timestamp":"2016-10-13T15:55:00+0200","id":124008,"name":"Johann","coordinate":{"longitude":11.50990009,"latitude":48.04550171},"fuelLevel":0.87,"lastAddress":"Gistlstraße 159, 82049 Pullach im Isartal, Germany"}
{"timestamp":"2016-10-13T15:55:00+0200","id":124039,"name":"Marie","coordinate":{"longitude":11.50949955,"latitude":48.04539871},"fuelLevel":0.9099999999999999,"lastAddress":"Seitnerstraße 70, 82049 Pullach im Isartal, Germany"}
{"timestamp":"2016-10-13T15:55:00+0200","id":124009,"name":"Ludwig","coordinate":{"longitude":11.58390045,"latitude":48.16230011},"fuelLevel":0.71,"lastAddress":"Herzogstraße 12, 80803 München, Germany"}
{"timestamp":"2016-10-13T15:55:00+0200","id":124007,"name":"Jakob","coordinate":{"longitude":11.57699966,"latitude":48.16659927},"fuelLevel":0.9400000000000001,"lastAddress":"Ansprengerstraße 25, 80803 München, Germany"}